mypackage/__init__.py
mypackage/decorators.py
mypackage/descriptors.py
mypackage/generators.py
mypackage/iterators.py
mypackage_pkg_tanyapeshkova-0.1.0.dist-info/METADATA
mypackage_pkg_tanyapeshkova-0.1.0.dist-info/WHEEL
mypackage_pkg_tanyapeshkova-0.1.0.dist-info/entry_points.txt
mypackage_pkg_tanyapeshkova-0.1.0.dist-info/top_level.txt
mypackage_pkg_tanyapeshkova-0.1.0.dist-info/RECORD
