Metadata-Version: 2.1
Name: mypackage-pkg-tanyapeshkova
Version: 0.1.0
Summary: Мой пакет с генераторами, итераторами, декораторами и дескрипторами
Home-page: https://github.com/TanyaPeshkova/mypackage
Author: TanyaPeshkova
Author-email: ваш@email.com
Classifier: Development Status :: 3 - Alpha
Classifier: Intended Audience :: Developers
Classifier: License :: OSI Approved :: MIT License
Classifier: Programming Language :: Python :: 3
Classifier: Programming Language :: Python :: 3.6
Classifier: Programming Language :: Python :: 3.7
Classifier: Programming Language :: Python :: 3.8
Classifier: Programming Language :: Python :: 3.9
Requires-Python: >=3.6
